{
  "$schema": "https://developer.microsoft.com/json-schemas/fabric/item/report/definition/visualContainer/2.7.0/schema.json",
  "name": "1e3780c587527047105c",
  "position": {
    "x": 14,
    "y": 6,
    "z": 0,
    "height": 215,
    "width": 479,
    "tabOrder": 0
  },
  "visual": {
    "visualType": "tableEx",
    "query": {
      "queryState": {
        "Values": {
          "projections": [
            {
              "field": {
                "Column": {
                  "Expression": {
                    "SourceRef": {
                      "Entity": "SalesData"
                    }
                  },
                  "Property": "Product Name"
                }
              },
              "queryRef": "SalesData.Product Name",
              "nativeQueryRef": "Product Name"
            },
            {
              "field": {
                "Measure": {
                  "Expression": {
                    "SourceRef": {
                      "Entity": "SalesData"
                    }
                  },
                  "Property": "Total Sales"
                }
              },
              "queryRef": "SalesData.Total Sales",
              "nativeQueryRef": "Total Sales"
            },
            {
              "field": {
                "Measure": {
                  "Expression": {
                    "SourceRef": {
                      "Entity": "SalesData"
                    }
                  },
                  "Property": "YOY Growth%"
                }
              },
              "queryRef": "SalesData.YOY Growth%",
              "nativeQueryRef": "YOY Growth%"
            }
          ]
        }
      },
      "sortDefinition": {
        "sort": [
          {
            "field": {
              "Measure": {
                "Expression": {
                  "SourceRef": {
                    "Entity": "SalesData"
                  }
                },
                "Property": "YOY Growth%"
              }
            },
            "direction": "Descending"
          }
        ]
      }
    },
    "objects": {
      "columnWidth": [
        {
          "properties": {
            "value": {
              "expr": {
                "Literal": {
                  "Value": "274D"
                }
              }
            }
          },
          "selector": {
            "metadata": "SalesData.Product Name"
          }
        },
        {
          "properties": {
            "value": {
              "expr": {
                "Literal": {
                  "Value": "72D"
                }
              }
            }
          },
          "selector": {
            "metadata": "SalesData.Total Sales"
          }
        }
      ],
      "columnHeaders": [
        {
          "properties": {
            "backColor": {
              "solid": {
                "color": {
                  "expr": {
                    "Literal": {
                      "Value": "'#0998D5'"
                    }
                  }
                }
              }
            },
            "fontColor": {
              "solid": {
                "color": {
                  "expr": {
                    "ThemeDataColor": {
                      "ColorId": 0,
                      "Percent": 0
                    }
                  }
                }
              }
            }
          }
        }
      ],
      "total": [
        {
          "properties": {
            "totals": {
              "expr": {
                "Literal": {
                  "Value": "false"
                }
              }
            }
          }
        }
      ]
    },
    "visualContainerObjects": {
      "title": [
        {
          "properties": {
            "show": {
              "expr": {
                "Literal": {
                  "Value": "true"
                }
              }
            },
            "text": {
              "expr": {
                "Literal": {
                  "Value": "'Top 5 Selling Proucts'"
                }
              }
            },
            "fontFamily": {
              "expr": {
                "Literal": {
                  "Value": "'''Arial Unicode MS'''"
                }
              }
            },
            "fontColor": {
              "solid": {
                "color": {
                  "expr": {
                    "Literal": {
                      "Value": "'#0998D5'"
                    }
                  }
                }
              }
            },
            "alignment": {
              "expr": {
                "Literal": {
                  "Value": "'center'"
                }
              }
            }
          }
        }
      ]
    },
    "drillFilterOtherVisuals": true
  },
  "filterConfig": {
    "filters": [
      {
        "name": "90d7e79538b56d34e177",
        "field": {
          "Column": {
            "Expression": {
              "SourceRef": {
                "Entity": "SalesData"
              }
            },
            "Property": "Product Name"
          }
        },
        "type": "TopN",
        "filter": {
          "Version": 2,
          "From": [
            {
              "Name": "subquery",
              "Expression": {
                "Subquery": {
                  "Query": {
                    "Version": 2,
                    "From": [
                      {
                        "Name": "s",
                        "Entity": "SalesData",
                        "Type": 0
                      }
                    ],
                    "Select": [
                      {
                        "Column": {
                          "Expression": {
                            "SourceRef": {
                              "Source": "s"
                            }
                          },
                          "Property": "Product Name"
                        },
                        "Name": "field"
                      }
                    ],
                    "OrderBy": [
                      {
                        "Direction": 2,
                        "Expression": {
                          "Measure": {
                            "Expression": {
                              "SourceRef": {
                                "Source": "s"
                              }
                            },
                            "Property": "Total Sales"
                          }
                        }
                      }
                    ],
                    "Top": 5
                  }
                }
              },
              "Type": 2
            },
            {
              "Name": "s",
              "Entity": "SalesData",
              "Type": 0
            }
          ],
          "Where": [
            {
              "Condition": {
                "In": {
                  "Expressions": [
                    {
                      "Column": {
                        "Expression": {
                          "SourceRef": {
                            "Source": "s"
                          }
                        },
                        "Property": "Product Name"
                      }
                    }
                  ],
                  "Table": {
                    "SourceRef": {
                      "Source": "subquery"
                    }
                  }
                }
              }
            }
          ]
        }
      }
    ]
  }
}